ikcode_devtools/__init__.py
ikcode_devtools/auto_reformatter.py
ikcode_devtools/gtest.py
ikcode_devtools/ikcode.png
ikcode_devtools/inspector.py
ikcode_devtools/main.py
ikcode_devtools/playgrounds.py
ikcode_devtools/regex_tester.py
ikcode_devtools/version.py
ikcode_devtools-2.3.1.dist-info/licenses/LICENSE
ikcode_devtools-2.3.1.dist-info/METADATA
ikcode_devtools-2.3.1.dist-info/WHEEL
ikcode_devtools-2.3.1.dist-info/entry_points.txt
ikcode_devtools-2.3.1.dist-info/top_level.txt
ikcode_devtools-2.3.1.dist-info/RECORD
